{"GlobalPropertiesHash":"2ilJ2M8+ZdH0swl4cXFj9Ji8kay0R08ISE/fEc+OL0o=","FingerprintPatternsHash":"8ZRc1sGeVrPBx4lD717BgRaQekyh78QKV9SKsdt638U=","PropertyOverridesHash":"8ZRc1sGeVrPBx4lD717BgRaQekyh78QKV9SKsdt638U=","InputHashes":["NiIWHJzh00vSiUrjeOA77K0AM7rZD\u002Bo0sKuR3uAiPaY=","rYP3bbFbVew5O/fLn00q/JbnjVty1dmO/iPx1E0ZfZU=","RP1tUBdpCfGIoU\u002BGC6PetVjtIe9VcHUZUrrSC0MS/2U=","TV1OXhL8j\u002BKVhFJ8C84/eql4\u002BHu836mDt04iAoLjxJQ=","\u002BAwqR2d/y8hqgcUuXhhMiTkZHMV\u002BHtB8mQBaEMgJTlE=","yGGUyHH5WyuVOkDebqt8QetNXfkgjynsv5kkOfKHzag=","hIYNOgwSutVa5\u002Bd34x4SxuYtIZks\u002Bx7og5VkZcxmvH8=","2cKFZ5k7TnCC0nEm\u002BUk9kIZ9Ah9FXxiKq58wIu35jKs=","Ncz03gr7zp1z/yK9zqHvHzcdCwu9/HOWqCAYq2ytFOM=","9sAIIU6lr6wqidipP8lDdjYWRBh7/JNqk3qgIFP386E=","15i9fpnk3I3ve4XyZAqfeWA8ScBgyquzS3rwGqqdghA=","2\u002B5gPy7zAq9SwA/\u002B4Q17w0nGKOJ\u002BCQpNBKPcQ9zBskI=","MQp9CtQh9gvSIpJuAyZNOxnFNMqQZYZzZk0gyLaNP0E=","vXNz5lnETifnRVxckKR7EjnD3aSD8Xh0pWPErA1lBNk=","YQ6X5Er8Bn6B27VAv\u002B0iYeNYWDlcLZbXukJaPcl09d8=","6RQiUlwCPiL9q6R8eLOBfGpIE6YU7W7Dc298s9Dvl3o=","cHst3wlSQNbzQTYrW60SokBUKQ3M52rnmru4pGGbyD4=","v3EhBX9jHdvaGyuWf8pHFm9tbhWGr426D6M04wkSPFc="],"CachedAssets":{"NiIWHJzh00vSiUrjeOA77K0AM7rZD\u002Bo0sKuR3uAiPaY=":{"Identity":"C:\\Users\\nbaig\\Downloads\\starter_code\\starter_code\\obj\\Debug\\net9.0\\compressed\\a4nj05w3a6-zijek7q4wg.gz","SourceId":"starter_code","SourceType":"Discovered","ContentRoot":"C:\\Users\\nbaig\\Downloads\\starter_code\\starter_code\\obj\\Debug\\net9.0\\compressed\\","BasePath":"_content/starter_code","RelativePath":"css/site#[.{fingerprint=zijek7q4wg}]?.css.gz","AssetKind":"All","AssetMode":"All","AssetRole":"Alternative","AssetMergeBehavior":null,"AssetMergeSource":"","RelatedAsset":"C:\\Users\\nbaig\\Downloads\\starter_code\\starter_code\\wwwroot\\css\\site.css","AssetTraitName":"Content-Encoding","AssetTraitValue":"gzip","Fingerprint":"o2tez8g7tu","Integrity":"sG265s1Esls1KBreZO66PtRZ08vZfcgam\u002BQ2Tb7\u002BiM4=","CopyToOutputDirectory":"Never","CopyToPublishDirectory":"PreserveNewest","OriginalItemSpec":"C:\\Users\\nbaig\\Downloads\\starter_code\\starter_code\\wwwroot\\css\\site.css","FileLength":166,"LastWriteTime":"2025-11-21T10:54:55.6994433+00:00"},"rYP3bbFbVew5O/fLn00q/JbnjVty1dmO/iPx1E0ZfZU=":{"Identity":"C:\\Users\\nbaig\\Downloads\\starter_code\\starter_code\\obj\\Debug\\net9.0\\compressed\\tkzcupom5g-61n19gt1b8.gz","SourceId":"starter_code","SourceType":"Discovered","ContentRoot":"C:\\Users\\nbaig\\Downloads\\starter_code\\starter_code\\obj\\Debug\\net9.0\\compressed\\","BasePath":"_content/starter_code","RelativePath":"favicon#[.{fingerprint=61n19gt1b8}]?.ico.gz","AssetKind":"All","AssetMode":"All","AssetRole":"Alternative","AssetMergeBehavior":null,"AssetMergeSource":"","RelatedAsset":"C:\\Users\\nbaig\\Downloads\\starter_code\\starter_code\\wwwroot\\favicon.ico","AssetTraitName":"Content-Encoding","AssetTraitValue":"gzip","Fingerprint":"lir1p715ud","Integrity":"jcY0RXFOlcp4VNTCcYQtWVZZBlr\u002BZY\u002BAOv6/0S5dnF8=","CopyToOutputDirectory":"Never","CopyToPublishDirectory":"PreserveNewest","OriginalItemSpec":"C:\\Users\\nbaig\\Downloads\\starter_code\\starter_code\\wwwroot\\favicon.ico","FileLength":2432,"LastWriteTime":"2025-11-21T10:54:55.7034092+00:00"},"RP1tUBdpCfGIoU\u002BGC6PetVjtIe9VcHUZUrrSC0MS/2U=":{"Identity":"C:\\Users\\nbaig\\Downloads\\starter_code\\starter_code\\obj\\Debug\\net9.0\\compressed\\pw2tb7ktu8-e1kigz27jf.gz","SourceId":"starter_code","SourceType":"Discovered","ContentRoot":"C:\\Users\\nbaig\\Downloads\\starter_code\\starter_code\\obj\\Debug\\net9.0\\compressed\\","BasePath":"_content/starter_code","RelativePath":"index#[.{fingerprint=e1kigz27jf}]?.html.gz","AssetKind":"All","AssetMode":"All","AssetRole":"Alternative","AssetMergeBehavior":null,"AssetMergeSource":"","RelatedAsset":"C:\\Users\\nbaig\\Downloads\\starter_code\\starter_code\\wwwroot\\index.html","AssetTraitName":"Content-Encoding","AssetTraitValue":"gzip","Fingerprint":"vh8vev3rdt","Integrity":"w9aFKQBJJUpW03jdIj1tk3UXgm6QvI6GpV2mN9mSguY=","CopyToOutputDirectory":"Never","CopyToPublishDirectory":"PreserveNewest","OriginalItemSpec":"C:\\Users\\nbaig\\Downloads\\starter_code\\starter_code\\wwwroot\\index.html","FileLength":2264,"LastWriteTime":"2025-11-25T11:53:00.8516957+00:00"},"6RQiUlwCPiL9q6R8eLOBfGpIE6YU7W7Dc298s9Dvl3o=":{"Identity":"C:\\Users\\nbaig\\Downloads\\starter_code\\starter_code\\obj\\Debug\\net9.0\\compressed\\gwa8e3stld-udrjapxh62.gz","SourceId":"starter_code","SourceType":"Discovered","ContentRoot":"C:\\Users\\nbaig\\Downloads\\starter_code\\starter_code\\obj\\Debug\\net9.0\\compressed\\","BasePath":"_content/starter_code","RelativePath":"js/site#[.{fingerprint=udrjapxh62}]?.js.gz","AssetKind":"All","AssetMode":"All","AssetRole":"Alternative","AssetMergeBehavior":null,"AssetMergeSource":"","RelatedAsset":"C:\\Users\\nbaig\\Downloads\\starter_code\\starter_code\\wwwroot\\js\\site.js","AssetTraitName":"Content-Encoding","AssetTraitValue":"gzip","Fingerprint":"5qbqx8f3lg","Integrity":"I7EItWppPAem6\u002BmCRUVhy0CJpBbCy481QrFbeW1X9OE=","CopyToOutputDirectory":"Never","CopyToPublishDirectory":"PreserveNewest","OriginalItemSpec":"C:\\Users\\nbaig\\Downloads\\starter_code\\starter_code\\wwwroot\\js\\site.js","FileLength":3047,"LastWriteTime":"2025-11-26T10:11:38.0372164+00:00"},"TV1OXhL8j\u002BKVhFJ8C84/eql4\u002BHu836mDt04iAoLjxJQ=":{"Identity":"C:\\Users\\nbaig\\Downloads\\starter_code\\starter_code\\obj\\Debug\\net9.0\\compressed\\164legzlsr-2vmb2j3pfy.gz","SourceId":"starter_code","SourceType":"Discovered","ContentRoot":"C:\\Users\\nbaig\\Downloads\\starter_code\\starter_code\\obj\\Debug\\net9.0\\compressed\\","BasePath":"_content/starter_code","RelativePath":"lib/jquery-validation-unobtrusive/jquery.validate.unobtrusive#[.{fingerprint=2vmb2j3pfy}]?.js.gz","AssetKind":"All","AssetMode":"All","AssetRole":"Alternative","AssetMergeBehavior":null,"AssetMergeSource":"","RelatedAsset":"C:\\Users\\nbaig\\Downloads\\starter_code\\starter_code\\wwwroot\\lib\\jquery-validation-unobtrusive\\jquery.validate.unobtrusive.js","AssetTraitName":"Content-Encoding","AssetTraitValue":"gzip","Fingerprint":"57uyb38cey","Integrity":"n9tTr3RBzbWz0w20EuRj3B095eOQGMVOZbxAOzqBXUs=","CopyToOutputDirectory":"Never","CopyToPublishDirectory":"PreserveNewest","OriginalItemSpec":"C:\\Users\\nbaig\\Downloads\\starter_code\\starter_code\\wwwroot\\lib\\jquery-validation-unobtrusive\\jquery.validate.unobtrusive.js","FileLength":4660,"LastWriteTime":"2025-11-21T10:54:55.7014055+00:00"},"\u002BAwqR2d/y8hqgcUuXhhMiTkZHMV\u002BHtB8mQBaEMgJTlE=":{"Identity":"C:\\Users\\nbaig\\Downloads\\starter_code\\starter_code\\obj\\Debug\\net9.0\\compressed\\ou33mqsxcg-4v8eqarkd7.gz","SourceId":"starter_code","SourceType":"Discovered","ContentRoot":"C:\\Users\\nbaig\\Downloads\\starter_code\\starter_code\\obj\\Debug\\net9.0\\compressed\\","BasePath":"_content/starter_code","RelativePath":"lib/jquery-validation-unobtrusive/jquery.validate.unobtrusive.min#[.{fingerprint=4v8eqarkd7}]?.js.gz","AssetKind":"All","AssetMode":"All","AssetRole":"Alternative","AssetMergeBehavior":null,"AssetMergeSource":"","RelatedAsset":"C:\\Users\\nbaig\\Downloads\\starter_code\\starter_code\\wwwroot\\lib\\jquery-validation-unobtrusive\\jquery.validate.unobtrusive.min.js","AssetTraitName":"Content-Encoding","AssetTraitValue":"gzip","Fingerprint":"tabrq1ho0f","Integrity":"9X\u002B6mMpWl0sRImYav09zbU/QCCt\u002BGeH7cDib6C/z2lI=","CopyToOutputDirectory":"Never","CopyToPublishDirectory":"PreserveNewest","OriginalItemSpec":"C:\\Users\\nbaig\\Downloads\\starter_code\\starter_code\\wwwroot\\lib\\jquery-validation-unobtrusive\\jquery.validate.unobtrusive.min.js","FileLength":2202,"LastWriteTime":"2025-11-21T10:54:55.7054283+00:00"},"yGGUyHH5WyuVOkDebqt8QetNXfkgjynsv5kkOfKHzag=":{"Identity":"C:\\Users\\nbaig\\Downloads\\starter_code\\starter_code\\obj\\Debug\\net9.0\\compressed\\j5yccctjsi-356vix0kms.gz","SourceId":"starter_code","SourceType":"Discovered","ContentRoot":"C:\\Users\\nbaig\\Downloads\\starter_code\\starter_code\\obj\\Debug\\net9.0\\compressed\\","BasePath":"_content/starter_code","RelativePath":"lib/jquery-validation-unobtrusive/LICENSE#[.{fingerprint=356vix0kms}]?.txt.gz","AssetKind":"All","AssetMode":"All","AssetRole":"Alternative","AssetMergeBehavior":null,"AssetMergeSource":"","RelatedAsset":"C:\\Users\\nbaig\\Downloads\\starter_code\\starter_code\\wwwroot\\lib\\jquery-validation-unobtrusive\\LICENSE.txt","AssetTraitName":"Content-Encoding","AssetTraitValue":"gzip","Fingerprint":"0vtotz30el","Integrity":"1HkjQSVuV0/ji/X/lGeDTHeagBS0BwopMrHDQuwqgtU=","CopyToOutputDirectory":"Never","CopyToPublishDirectory":"PreserveNewest","OriginalItemSpec":"C:\\Users\\nbaig\\Downloads\\starter_code\\starter_code\\wwwroot\\lib\\jquery-validation-unobtrusive\\LICENSE.txt","FileLength":680,"LastWriteTime":"2025-11-21T10:54:55.6994433+00:00"},"hIYNOgwSutVa5\u002Bd34x4SxuYtIZks\u002Bx7og5VkZcxmvH8=":{"Identity":"C:\\Users\\nbaig\\Downloads\\starter_code\\starter_code\\obj\\Debug\\net9.0\\compressed\\v2msyy1cqu-9lzv6zm51u.gz","SourceId":"starter_code","SourceType":"Discovered","ContentRoot":"C:\\Users\\nbaig\\Downloads\\starter_code\\starter_code\\obj\\Debug\\net9.0\\compressed\\","BasePath":"_content/starter_code","RelativePath":"lib/jquery-validation/dist/additional-methods#[.{fingerprint=9lzv6zm51u}]?.js.gz","AssetKind":"All","AssetMode":"All","AssetRole":"Alternative","AssetMergeBehavior":null,"AssetMergeSource":"","RelatedAsset":"C:\\Users\\nbaig\\Downloads\\starter_code\\starter_code\\wwwroot\\lib\\jquery-validation\\dist\\additional-methods.js","AssetTraitName":"Content-Encoding","AssetTraitValue":"gzip","Fingerprint":"y7h6l82g77","Integrity":"rhF5wOMHkgEiWNEm\u002BGdg\u002BktB8u3\u002BWd\u002BGpMqSgc8OjNE=","CopyToOutputDirectory":"Never","CopyToPublishDirectory":"PreserveNewest","OriginalItemSpec":"C:\\Users\\nbaig\\Downloads\\starter_code\\starter_code\\wwwroot\\lib\\jquery-validation\\dist\\additional-methods.js","FileLength":14216,"LastWriteTime":"2025-11-21T10:54:55.7074335+00:00"},"2cKFZ5k7TnCC0nEm\u002BUk9kIZ9Ah9FXxiKq58wIu35jKs=":{"Identity":"C:\\Users\\nbaig\\Downloads\\starter_code\\starter_code\\obj\\Debug\\net9.0\\compressed\\w08pvc38jf-9oaff4kq20.gz","SourceId":"starter_code","SourceType":"Discovered","ContentRoot":"C:\\Users\\nbaig\\Downloads\\starter_code\\starter_code\\obj\\Debug\\net9.0\\compressed\\","BasePath":"_content/starter_code","RelativePath":"lib/jquery-validation/dist/additional-methods.min#[.{fingerprint=9oaff4kq20}]?.js.gz","AssetKind":"All","AssetMode":"All","AssetRole":"Alternative","AssetMergeBehavior":null,"AssetMergeSource":"","RelatedAsset":"C:\\Users\\nbaig\\Downloads\\starter_code\\starter_code\\wwwroot\\lib\\jquery-validation\\dist\\additional-methods.min.js","AssetTraitName":"Content-Encoding","AssetTraitValue":"gzip","Fingerprint":"j054byf56j","Integrity":"nSo\u002B4/uUtabmWWlaeIyHzzD02IgPpFO4Xtd0N7gk/Nk=","CopyToOutputDirectory":"Never","CopyToPublishDirectory":"PreserveNewest","OriginalItemSpec":"C:\\Users\\nbaig\\Downloads\\starter_code\\starter_code\\wwwroot\\lib\\jquery-validation\\dist\\additional-methods.min.js","FileLength":6420,"LastWriteTime":"2025-11-21T10:54:55.7014055+00:00"},"Ncz03gr7zp1z/yK9zqHvHzcdCwu9/HOWqCAYq2ytFOM=":{"Identity":"C:\\Users\\nbaig\\Downloads\\starter_code\\starter_code\\obj\\Debug\\net9.0\\compressed\\niwqtki7h8-gqog8p0ftl.gz","SourceId":"starter_code","SourceType":"Discovered","ContentRoot":"C:\\Users\\nbaig\\Downloads\\starter_code\\starter_code\\obj\\Debug\\net9.0\\compressed\\","BasePath":"_content/starter_code","RelativePath":"lib/jquery-validation/dist/jquery.validate#[.{fingerprint=gqog8p0ftl}]?.js.gz","AssetKind":"All","AssetMode":"All","AssetRole":"Alternative","AssetMergeBehavior":null,"AssetMergeSource":"","RelatedAsset":"C:\\Users\\nbaig\\Downloads\\starter_code\\starter_code\\wwwroot\\lib\\jquery-validation\\dist\\jquery.validate.js","AssetTraitName":"Content-Encoding","AssetTraitValue":"gzip","Fingerprint":"80o7filfy5","Integrity":"SHzdcrIo8Qh7C8AQB\u002BlBOiP32HP0hEflJq9gOhkpJKY=","CopyToOutputDirectory":"Never","CopyToPublishDirectory":"PreserveNewest","OriginalItemSpec":"C:\\Users\\nbaig\\Downloads\\starter_code\\starter_code\\wwwroot\\lib\\jquery-validation\\dist\\jquery.validate.js","FileLength":14588,"LastWriteTime":"2025-11-21T10:54:55.7094406+00:00"},"9sAIIU6lr6wqidipP8lDdjYWRBh7/JNqk3qgIFP386E=":{"Identity":"C:\\Users\\nbaig\\Downloads\\starter_code\\starter_code\\obj\\Debug\\net9.0\\compressed\\dbkg1eftcm-b7iojwaux1.gz","SourceId":"starter_code","SourceType":"Discovered","ContentRoot":"C:\\Users\\nbaig\\Downloads\\starter_code\\starter_code\\obj\\Debug\\net9.0\\compressed\\","BasePath":"_content/starter_code","RelativePath":"lib/jquery-validation/dist/jquery.validate.min#[.{fingerprint=b7iojwaux1}]?.js.gz","AssetKind":"All","AssetMode":"All","AssetRole":"Alternative","AssetMergeBehavior":null,"AssetMergeSource":"","RelatedAsset":"C:\\Users\\nbaig\\Downloads\\starter_code\\starter_code\\wwwroot\\lib\\jquery-validation\\dist\\jquery.validate.min.js","AssetTraitName":"Content-Encoding","AssetTraitValue":"gzip","Fingerprint":"bkil41cbdh","Integrity":"xQa9J1VTjjrTxirEIyj\u002BEvbdJZI8eAX38XFi4mY\u002BEu0=","CopyToOutputDirectory":"Never","CopyToPublishDirectory":"PreserveNewest","OriginalItemSpec":"C:\\Users\\nbaig\\Downloads\\starter_code\\starter_code\\wwwroot\\lib\\jquery-validation\\dist\\jquery.validate.min.js","FileLength":7917,"LastWriteTime":"2025-11-21T10:54:55.7034092+00:00"},"15i9fpnk3I3ve4XyZAqfeWA8ScBgyquzS3rwGqqdghA=":{"Identity":"C:\\Users\\nbaig\\Downloads\\starter_code\\starter_code\\obj\\Debug\\net9.0\\compressed\\y9k6i6s349-x0q3zqp4vz.gz","SourceId":"starter_code","SourceType":"Discovered","ContentRoot":"C:\\Users\\nbaig\\Downloads\\starter_code\\starter_code\\obj\\Debug\\net9.0\\compressed\\","BasePath":"_content/starter_code","RelativePath":"lib/jquery-validation/LICENSE#[.{fingerprint=x0q3zqp4vz}]?.md.gz","AssetKind":"All","AssetMode":"All","AssetRole":"Alternative","AssetMergeBehavior":null,"AssetMergeSource":"","RelatedAsset":"C:\\Users\\nbaig\\Downloads\\starter_code\\starter_code\\wwwroot\\lib\\jquery-validation\\LICENSE.md","AssetTraitName":"Content-Encoding","AssetTraitValue":"gzip","Fingerprint":"tbedkqp182","Integrity":"yZU1lf/p2dEnCHUXYp8G4roAyod23x5MoR4DehwHfrA=","CopyToOutputDirectory":"Never","CopyToPublishDirectory":"PreserveNewest","OriginalItemSpec":"C:\\Users\\nbaig\\Downloads\\starter_code\\starter_code\\wwwroot\\lib\\jquery-validation\\LICENSE.md","FileLength":670,"LastWriteTime":"2025-11-21T10:54:55.7054283+00:00"},"2\u002B5gPy7zAq9SwA/\u002B4Q17w0nGKOJ\u002BCQpNBKPcQ9zBskI=":{"Identity":"C:\\Users\\nbaig\\Downloads\\starter_code\\starter_code\\obj\\Debug\\net9.0\\compressed\\90yn11ozbs-zqklsrm5rb.gz","SourceId":"starter_code","SourceType":"Discovered","ContentRoot":"C:\\Users\\nbaig\\Downloads\\starter_code\\starter_code\\obj\\Debug\\net9.0\\compressed\\","BasePath":"_content/starter_code","RelativePath":"lib/jquery/dist/jquery#[.{fingerprint=zqklsrm5rb}]?.js.gz","AssetKind":"All","AssetMode":"All","AssetRole":"Alternative","AssetMergeBehavior":null,"AssetMergeSource":"","RelatedAsset":"C:\\Users\\nbaig\\Downloads\\starter_code\\starter_code\\wwwroot\\lib\\jquery\\dist\\jquery.js","AssetTraitName":"Content-Encoding","AssetTraitValue":"gzip","Fingerprint":"qx7pkpohtj","Integrity":"krPuVmhGZKDd/mCx5wnT1kk9tcdum3/9BrAV9baQnh8=","CopyToOutputDirectory":"Never","CopyToPublishDirectory":"PreserveNewest","OriginalItemSpec":"C:\\Users\\nbaig\\Downloads\\starter_code\\starter_code\\wwwroot\\lib\\jquery\\dist\\jquery.js","FileLength":91975,"LastWriteTime":"2025-11-21T10:54:55.7238729+00:00"},"MQp9CtQh9gvSIpJuAyZNOxnFNMqQZYZzZk0gyLaNP0E=":{"Identity":"C:\\Users\\nbaig\\Downloads\\starter_code\\starter_code\\obj\\Debug\\net9.0\\compressed\\kbp8brfvp6-dd6z7egasc.gz","SourceId":"starter_code","SourceType":"Discovered","ContentRoot":"C:\\Users\\nbaig\\Downloads\\starter_code\\starter_code\\obj\\Debug\\net9.0\\compressed\\","BasePath":"_content/starter_code","RelativePath":"lib/jquery/dist/jquery.min#[.{fingerprint=dd6z7egasc}]?.js.gz","AssetKind":"All","AssetMode":"All","AssetRole":"Alternative","AssetMergeBehavior":null,"AssetMergeSource":"","RelatedAsset":"C:\\Users\\nbaig\\Downloads\\starter_code\\starter_code\\wwwroot\\lib\\jquery\\dist\\jquery.min.js","AssetTraitName":"Content-Encoding","AssetTraitValue":"gzip","Fingerprint":"7pi76fr1u9","Integrity":"lVOaS5HHoPiJvrr2uXW7gHNWFhsLK9jeO1zdzSrZIR4=","CopyToOutputDirectory":"Never","CopyToPublishDirectory":"PreserveNewest","OriginalItemSpec":"C:\\Users\\nbaig\\Downloads\\starter_code\\starter_code\\wwwroot\\lib\\jquery\\dist\\jquery.min.js","FileLength":30947,"LastWriteTime":"2025-11-21T10:54:55.7136118+00:00"},"vXNz5lnETifnRVxckKR7EjnD3aSD8Xh0pWPErA1lBNk=":{"Identity":"C:\\Users\\nbaig\\Downloads\\starter_code\\starter_code\\obj\\Debug\\net9.0\\compressed\\4diio8qmtj-5pze98is44.gz","SourceId":"starter_code","SourceType":"Discovered","ContentRoot":"C:\\Users\\nbaig\\Downloads\\starter_code\\starter_code\\obj\\Debug\\net9.0\\compressed\\","BasePath":"_content/starter_code","RelativePath":"lib/jquery/dist/jquery.min#[.{fingerprint=5pze98is44}]?.map.gz","AssetKind":"All","AssetMode":"All","AssetRole":"Alternative","AssetMergeBehavior":null,"AssetMergeSource":"","RelatedAsset":"C:\\Users\\nbaig\\Downloads\\starter_code\\starter_code\\wwwroot\\lib\\jquery\\dist\\jquery.min.map","AssetTraitName":"Content-Encoding","AssetTraitValue":"gzip","Fingerprint":"mj31qw4xg4","Integrity":"MiLC1UUkHkFmJt7jHaqnI08J/ulRHDYz8gHORCuebkc=","CopyToOutputDirectory":"Never","CopyToPublishDirectory":"PreserveNewest","OriginalItemSpec":"C:\\Users\\nbaig\\Downloads\\starter_code\\starter_code\\wwwroot\\lib\\jquery\\dist\\jquery.min.map","FileLength":55191,"LastWriteTime":"2025-11-21T10:54:55.7213661+00:00"},"YQ6X5Er8Bn6B27VAv\u002B0iYeNYWDlcLZbXukJaPcl09d8=":{"Identity":"C:\\Users\\nbaig\\Downloads\\starter_code\\starter_code\\obj\\Debug\\net9.0\\compressed\\m1qe3fjtq6-mlv21k5csn.gz","SourceId":"starter_code","SourceType":"Discovered","ContentRoot":"C:\\Users\\nbaig\\Downloads\\starter_code\\starter_code\\obj\\Debug\\net9.0\\compressed\\","BasePath":"_content/starter_code","RelativePath":"lib/jquery/LICENSE#[.{fingerprint=mlv21k5csn}]?.txt.gz","AssetKind":"All","AssetMode":"All","AssetRole":"Alternative","AssetMergeBehavior":null,"AssetMergeSource":"","RelatedAsset":"C:\\Users\\nbaig\\Downloads\\starter_code\\starter_code\\wwwroot\\lib\\jquery\\LICENSE.txt","AssetTraitName":"Content-Encoding","AssetTraitValue":"gzip","Fingerprint":"rdl0higpfn","Integrity":"wRqs30CSrwWDvG1bDMUjomAlSqRRTMplLSuLcrgYtHw=","CopyToOutputDirectory":"Never","CopyToPublishDirectory":"PreserveNewest","OriginalItemSpec":"C:\\Users\\nbaig\\Downloads\\starter_code\\starter_code\\wwwroot\\lib\\jquery\\LICENSE.txt","FileLength":669,"LastWriteTime":"2025-11-21T10:54:55.7094406+00:00"},"cHst3wlSQNbzQTYrW60SokBUKQ3M52rnmru4pGGbyD4=":{"Identity":"C:\\Users\\nbaig\\Downloads\\starter_code\\starter_code\\obj\\Debug\\net9.0\\compressed\\n3tby1pbkw-p0rixeoyew.gz","SourceId":"starter_code","SourceType":"Computed","ContentRoot":"C:\\Users\\nbaig\\Downloads\\starter_code\\starter_code\\obj\\Debug\\net9.0\\compressed\\","BasePath":"_content/starter_code","RelativePath":"starter_code#[.{fingerprint=p0rixeoyew}]?.styles.css.gz","AssetKind":"All","AssetMode":"CurrentProject","AssetRole":"Alternative","AssetMergeBehavior":null,"AssetMergeSource":"","RelatedAsset":"C:\\Users\\nbaig\\Downloads\\starter_code\\starter_code\\obj\\Debug\\net9.0\\scopedcss\\bundle\\starter_code.styles.css","AssetTraitName":"Content-Encoding","AssetTraitValue":"gzip","Fingerprint":"a0rzx89yth","Integrity":"emSZKwpEztkheNIiN4fj63nbZR09U7O7Vws3Fso4sNc=","CopyToOutputDirectory":"Never","CopyToPublishDirectory":"PreserveNewest","OriginalItemSpec":"C:\\Users\\nbaig\\Downloads\\starter_code\\starter_code\\obj\\Debug\\net9.0\\scopedcss\\bundle\\starter_code.styles.css","FileLength":537,"LastWriteTime":"2025-11-21T10:54:55.7034092+00:00"},"v3EhBX9jHdvaGyuWf8pHFm9tbhWGr426D6M04wkSPFc=":{"Identity":"C:\\Users\\nbaig\\Downloads\\starter_code\\starter_code\\obj\\Debug\\net9.0\\compressed\\6tadt2n8lj-p0rixeoyew.gz","SourceId":"starter_code","SourceType":"Computed","ContentRoot":"C:\\Users\\nbaig\\Downloads\\starter_code\\starter_code\\obj\\Debug\\net9.0\\compressed\\","BasePath":"_content/starter_code","RelativePath":"starter_code#[.{fingerprint=p0rixeoyew}]!.bundle.scp.css.gz","AssetKind":"All","AssetMode":"Reference","AssetRole":"Alternative","AssetMergeBehavior":null,"AssetMergeSource":"","RelatedAsset":"C:\\Users\\nbaig\\Downloads\\starter_code\\starter_code\\obj\\Debug\\net9.0\\scopedcss\\projectbundle\\starter_code.bundle.scp.css","AssetTraitName":"Content-Encoding","AssetTraitValue":"gzip","Fingerprint":"a0rzx89yth","Integrity":"emSZKwpEztkheNIiN4fj63nbZR09U7O7Vws3Fso4sNc=","CopyToOutputDirectory":"Never","CopyToPublishDirectory":"PreserveNewest","OriginalItemSpec":"C:\\Users\\nbaig\\Downloads\\starter_code\\starter_code\\obj\\Debug\\net9.0\\scopedcss\\projectbundle\\starter_code.bundle.scp.css","FileLength":537,"LastWriteTime":"2025-11-21T10:54:55.7094406+00:00"}},"CachedCopyCandidates":{}}